{"nodes": [{"id": "backend_02_features_05_monitoring_workers_runner_py", "label": "runner.py", "file_type": "code", "source_file": "backend/02_features/05_monitoring/workers/runner.py", "source_location": "L1"}, {"id": "runner_workerstate", "label": "WorkerState", "file_type": "code", "source_file": "backend/02_features/05_monitoring/workers/runner.py", "source_location": "L35"}, {"id": "runner_workerstate_init", "label": ".__init__()", "file_type": "code", "source_file": "backend/02_features/05_monitoring/workers/runner.py", "source_location": "L36"}, {"id": "runner_workerstate_snapshot", "label": ".snapshot()", "file_type": "code", "source_file": "backend/02_features/05_monitoring/workers/runner.py", "source_location": "L43"}, {"id": "runner_workerpool", "label": "WorkerPool", "file_type": "code", "source_file": "backend/02_features/05_monitoring/workers/runner.py", "source_location": "L53"}, {"id": "runner_workerpool_init", "label": ".__init__()", "file_type": "code", "source_file": "backend/02_features/05_monitoring/workers/runner.py", "source_location": "L56"}, {"id": "runner_workerpool_backoff", "label": "._backoff()", "file_type": "code", "source_file": "backend/02_features/05_monitoring/workers/runner.py", "source_location": "L64"}, {"id": "runner_workerpool_supervised", "label": "._supervised()", "file_type": "code", "source_file": "backend/02_features/05_monitoring/workers/runner.py", "source_location": "L73"}, {"id": "runner_workerpool_start", "label": ".start()", "file_type": "code", "source_file": "backend/02_features/05_monitoring/workers/runner.py", "source_location": "L101"}, {"id": "runner_workerpool_stop", "label": ".stop()", "file_type": "code", "source_file": "backend/02_features/05_monitoring/workers/runner.py", "source_location": "L207"}, {"id": "runner_workerpool_health", "label": ".health()", "file_type": "code", "source_file": "backend/02_features/05_monitoring/workers/runner.py", "source_location": "L224"}, {"id": "runner_rationale_1", "label": "WorkerPool supervisor.  Spawns the 3 monitoring workers as asyncio tasks, each w", "file_type": "rationale", "source_file": "backend/02_features/05_monitoring/workers/runner.py", "source_location": "L1"}, {"id": "runner_rationale_54", "label": "Supervises monitoring workers. Designed to be started in FastAPI lifespan.", "file_type": "rationale", "source_file": "backend/02_features/05_monitoring/workers/runner.py", "source_location": "L54"}, {"id": "runner_rationale_102", "label": "Start supervised workers.          ``js`` may be None when NATS is unavailable \u2014", "file_type": "rationale", "source_file": "backend/02_features/05_monitoring/workers/runner.py", "source_location": "L102"}, {"id": "runner_rationale_208", "label": "Cancel all workers; wait up to ``timeout`` seconds for drain.", "file_type": "rationale", "source_file": "backend/02_features/05_monitoring/workers/runner.py", "source_location": "L208"}, {"id": "runner_rationale_225", "label": "Return per-worker health snapshot.", "file_type": "rationale", "source_file": "backend/02_features/05_monitoring/workers/runner.py", "source_location": "L225"}], "edges": [{"source": "backend_02_features_05_monitoring_workers_runner_py", "target": "asyncio", "relation": "imports", "confidence": "EXTRACTED", "source_file": "backend/02_features/05_monitoring/workers/runner.py", "source_location": "L11", "weight": 1.0}, {"source": "backend_02_features_05_monitoring_workers_runner_py", "target": "logging", "relation": "imports", "confidence": "EXTRACTED", "source_file": "backend/02_features/05_monitoring/workers/runner.py", "source_location": "L12", "weight": 1.0}, {"source": "backend_02_features_05_monitoring_workers_runner_py", "target": "datetime", "relation": "imports_from", "confidence": "EXTRACTED", "source_file": "backend/02_features/05_monitoring/workers/runner.py", "source_location": "L13", "weight": 1.0}, {"source": "backend_02_features_05_monitoring_workers_runner_py", "target": "importlib", "relation": "imports_from", "confidence": "EXTRACTED", "source_file": "backend/02_features/05_monitoring/workers/runner.py", "source_location": "L14", "weight": 1.0}, {"source": "backend_02_features_05_monitoring_workers_runner_py", "target": "typing", "relation": "imports_from", "confidence": "EXTRACTED", "source_file": "backend/02_features/05_monitoring/workers/runner.py", "source_location": "L15", "weight": 1.0}, {"source": "backend_02_features_05_monitoring_workers_runner_py", "target": "runner_workerstate", "relation": "contains", "confidence": "EXTRACTED", "source_file": "backend/02_features/05_monitoring/workers/runner.py", "source_location": "L35", "weight": 1.0}, {"source": "runner_workerstate", "target": "runner_workerstate_init", "relation": "method", "confidence": "EXTRACTED", "source_file": "backend/02_features/05_monitoring/workers/runner.py", "source_location": "L36", "weight": 1.0}, {"source": "runner_workerstate", "target": "runner_workerstate_snapshot", "relation": "method", "confidence": "EXTRACTED", "source_file": "backend/02_features/05_monitoring/workers/runner.py", "source_location": "L43", "weight": 1.0}, {"source": "backend_02_features_05_monitoring_workers_runner_py", "target": "runner_workerpool", "relation": "contains", "confidence": "EXTRACTED", "source_file": "backend/02_features/05_monitoring/workers/runner.py", "source_location": "L53", "weight": 1.0}, {"source": "runner_workerpool", "target": "runner_workerpool_init", "relation": "method", "confidence": "EXTRACTED", "source_file": "backend/02_features/05_monitoring/workers/runner.py", "source_location": "L56", "weight": 1.0}, {"source": "runner_workerpool", "target": "runner_workerpool_backoff", "relation": "method", "confidence": "EXTRACTED", "source_file": "backend/02_features/05_monitoring/workers/runner.py", "source_location": "L64", "weight": 1.0}, {"source": "runner_workerpool", "target": "runner_workerpool_supervised", "relation": "method", "confidence": "EXTRACTED", "source_file": "backend/02_features/05_monitoring/workers/runner.py", "source_location": "L73", "weight": 1.0}, {"source": "runner_workerpool", "target": "runner_workerpool_start", "relation": "method", "confidence": "EXTRACTED", "source_file": "backend/02_features/05_monitoring/workers/runner.py", "source_location": "L101", "weight": 1.0}, {"source": "runner_workerpool", "target": "runner_workerpool_stop", "relation": "method", "confidence": "EXTRACTED", "source_file": "backend/02_features/05_monitoring/workers/runner.py", "source_location": "L207", "weight": 1.0}, {"source": "runner_workerpool", "target": "runner_workerpool_health", "relation": "method", "confidence": "EXTRACTED", "source_file": "backend/02_features/05_monitoring/workers/runner.py", "source_location": "L224", "weight": 1.0}, {"source": "runner_workerpool_supervised", "target": "runner_workerpool_backoff", "relation": "calls", "confidence": "EXTRACTED", "source_file": "backend/02_features/05_monitoring/workers/runner.py", "source_location": "L90", "weight": 1.0}, {"source": "runner_workerpool_start", "target": "runner_workerstate", "relation": "calls", "confidence": "EXTRACTED", "source_file": "backend/02_features/05_monitoring/workers/runner.py", "source_location": "L130", "weight": 1.0}, {"source": "runner_workerpool_start", "target": "runner_workerpool_supervised", "relation": "calls", "confidence": "EXTRACTED", "source_file": "backend/02_features/05_monitoring/workers/runner.py", "source_location": "L132", "weight": 1.0}, {"source": "runner_workerpool_health", "target": "runner_workerstate_snapshot", "relation": "calls", "confidence": "EXTRACTED", "source_file": "backend/02_features/05_monitoring/workers/runner.py", "source_location": "L234", "weight": 1.0}, {"source": "runner_rationale_1", "target": "backend_02_features_05_monitoring_workers_runner_py", "relation": "rationale_for", "confidence": "EXTRACTED", "source_file": "backend/02_features/05_monitoring/workers/runner.py", "source_location": "L1", "weight": 1.0}, {"source": "runner_rationale_54", "target": "runner_workerpool", "relation": "rationale_for", "confidence": "EXTRACTED", "source_file": "backend/02_features/05_monitoring/workers/runner.py", "source_location": "L54", "weight": 1.0}, {"source": "runner_rationale_102", "target": "runner_workerpool_start", "relation": "rationale_for", "confidence": "EXTRACTED", "source_file": "backend/02_features/05_monitoring/workers/runner.py", "source_location": "L102", "weight": 1.0}, {"source": "runner_rationale_208", "target": "runner_workerpool_stop", "relation": "rationale_for", "confidence": "EXTRACTED", "source_file": "backend/02_features/05_monitoring/workers/runner.py", "source_location": "L208", "weight": 1.0}, {"source": "runner_rationale_225", "target": "runner_workerpool_health", "relation": "rationale_for", "confidence": "EXTRACTED", "source_file": "backend/02_features/05_monitoring/workers/runner.py", "source_location": "L225", "weight": 1.0}], "raw_calls": [{"caller_nid": "runner_workerstate_snapshot", "callee": "isoformat", "source_file": "backend/02_features/05_monitoring/workers/runner.py", "source_location": "L47"}, {"caller_nid": "runner_workerpool_backoff", "callee": "float", "source_file": "backend/02_features/05_monitoring/workers/runner.py", "source_location": "L71"}, {"caller_nid": "runner_workerpool_backoff", "callee": "min", "source_file": "backend/02_features/05_monitoring/workers/runner.py", "source_location": "L71"}, {"caller_nid": "runner_workerpool_backoff", "callee": "len", "source_file": "backend/02_features/05_monitoring/workers/runner.py", "source_location": "L71"}, {"caller_nid": "runner_workerpool_supervised", "callee": "factory", "source_file": "backend/02_features/05_monitoring/workers/runner.py", "source_location": "L79"}, {"caller_nid": "runner_workerpool_supervised", "callee": "repr", "source_file": "backend/02_features/05_monitoring/workers/runner.py", "source_location": "L89"}, {"caller_nid": "runner_workerpool_supervised", "callee": "warning", "source_file": "backend/02_features/05_monitoring/workers/runner.py", "source_location": "L91"}, {"caller_nid": "runner_workerpool_supervised", "callee": "sleep", "source_file": "backend/02_features/05_monitoring/workers/runner.py", "source_location": "L97"}, {"caller_nid": "runner_workerpool_start", "callee": "RedactionEngine", "source_file": "backend/02_features/05_monitoring/workers/runner.py", "source_location": "L107"}, {"caller_nid": "runner_workerpool_start", "callee": "load_config", "source_file": "backend/02_features/05_monitoring/workers/runner.py", "source_location": "L115"}, {"caller_nid": "runner_workerpool_start", "callee": "getattr", "source_file": "backend/02_features/05_monitoring/workers/runner.py", "source_location": "L116"}, {"caller_nid": "runner_workerpool_start", "callee": "import_module", "source_file": "backend/02_features/05_monitoring/workers/runner.py", "source_location": "L118"}, {"caller_nid": "runner_workerpool_start", "callee": "acquire", "source_file": "backend/02_features/05_monitoring/workers/runner.py", "source_location": "L121"}, {"caller_nid": "runner_workerpool_start", "callee": "get_by_slug", "source_file": "backend/02_features/05_monitoring/workers/runner.py", "source_location": "L122"}, {"caller_nid": "runner_workerpool_start", "callee": "LogsConsumer", "source_file": "backend/02_features/05_monitoring/workers/runner.py", "source_location": "L128"}, {"caller_nid": "runner_workerpool_start", "callee": "append", "source_file": "backend/02_features/05_monitoring/workers/runner.py", "source_location": "L131"}, {"caller_nid": "runner_workerpool_start", "callee": "create_task", "source_file": "backend/02_features/05_monitoring/workers/runner.py", "source_location": "L131"}, {"caller_nid": "runner_workerpool_start", "callee": "SpansConsumer", "source_file": "backend/02_features/05_monitoring/workers/runner.py", "source_location": "L136"}, {"caller_nid": "runner_workerpool_start", "callee": "append", "source_file": "backend/02_features/05_monitoring/workers/runner.py", "source_location": "L139"}, {"caller_nid": "runner_workerpool_start", "callee": "create_task", "source_file": "backend/02_features/05_monitoring/workers/runner.py", "source_location": "L139"}, {"caller_nid": "runner_workerpool_start", "callee": "getattr", "source_file": "backend/02_features/05_monitoring/workers/runner.py", "source_location": "L144"}, {"caller_nid": "runner_workerpool_start", "callee": "ApisixScraper", "source_file": "backend/02_features/05_monitoring/workers/runner.py", "source_location": "L145"}, {"caller_nid": "runner_workerpool_start", "callee": "append", "source_file": "backend/02_features/05_monitoring/workers/runner.py", "source_location": "L148"}, {"caller_nid": "runner_workerpool_start", "callee": "create_task", "source_file": "backend/02_features/05_monitoring/workers/runner.py", "source_location": "L148"}, {"caller_nid": "runner_workerpool_start", "callee": "getattr", "source_file": "backend/02_features/05_monitoring/workers/runner.py", "source_location": "L154"}, {"caller_nid": "runner_workerpool_start", "callee": "RollupScheduler", "source_file": "backend/02_features/05_monitoring/workers/runner.py", "source_location": "L155"}, {"caller_nid": "runner_workerpool_start", "callee": "append", "source_file": "backend/02_features/05_monitoring/workers/runner.py", "source_location": "L158"}, {"caller_nid": "runner_workerpool_start", "callee": "create_task", "source_file": "backend/02_features/05_monitoring/workers/runner.py", "source_location": "L158"}, {"caller_nid": "runner_workerpool_start", "callee": "getattr", "source_file": "backend/02_features/05_monitoring/workers/runner.py", "source_location": "L164"}, {"caller_nid": "runner_workerpool_start", "callee": "PartitionManager", "source_file": "backend/02_features/05_monitoring/workers/runner.py", "source_location": "L165"}, {"caller_nid": "runner_workerpool_start", "callee": "append", "source_file": "backend/02_features/05_monitoring/workers/runner.py", "source_location": "L168"}, {"caller_nid": "runner_workerpool_start", "callee": "create_task", "source_file": "backend/02_features/05_monitoring/workers/runner.py", "source_location": "L168"}, {"caller_nid": "runner_workerpool_start", "callee": "getattr", "source_file": "backend/02_features/05_monitoring/workers/runner.py", "source_location": "L174"}, {"caller_nid": "runner_workerpool_start", "callee": "SyntheticRunner", "source_file": "backend/02_features/05_monitoring/workers/runner.py", "source_location": "L175"}, {"caller_nid": "runner_workerpool_start", "callee": "append", "source_file": "backend/02_features/05_monitoring/workers/runner.py", "source_location": "L178"}, {"caller_nid": "runner_workerpool_start", "callee": "create_task", "source_file": "backend/02_features/05_monitoring/workers/runner.py", "source_location": "L178"}, {"caller_nid": "runner_workerpool_start", "callee": "getattr", "source_file": "backend/02_features/05_monitoring/workers/runner.py", "source_location": "L184"}, {"caller_nid": "runner_workerpool_start", "callee": "getattr", "source_file": "backend/02_features/05_monitoring/workers/runner.py", "source_location": "L185"}, {"caller_nid": "runner_workerpool_start", "callee": "NotifyListener", "source_file": "backend/02_features/05_monitoring/workers/runner.py", "source_location": "L187"}, {"caller_nid": "runner_workerpool_start", "callee": "append", "source_file": "backend/02_features/05_monitoring/workers/runner.py", "source_location": "L190"}, {"caller_nid": "runner_workerpool_start", "callee": "create_task", "source_file": "backend/02_features/05_monitoring/workers/runner.py", "source_location": "L190"}, {"caller_nid": "runner_workerpool_start", "callee": "getattr", "source_file": "backend/02_features/05_monitoring/workers/runner.py", "source_location": "L196"}, {"caller_nid": "runner_workerpool_start", "callee": "AlertEvaluatorWorker", "source_file": "backend/02_features/05_monitoring/workers/runner.py", "source_location": "L197"}, {"caller_nid": "runner_workerpool_start", "callee": "append", "source_file": "backend/02_features/05_monitoring/workers/runner.py", "source_location": "L200"}, {"caller_nid": "runner_workerpool_start", "callee": "create_task", "source_file": "backend/02_features/05_monitoring/workers/runner.py", "source_location": "L200"}, {"caller_nid": "runner_workerpool_start", "callee": "info", "source_file": "backend/02_features/05_monitoring/workers/runner.py", "source_location": "L205"}, {"caller_nid": "runner_workerpool_start", "callee": "len", "source_file": "backend/02_features/05_monitoring/workers/runner.py", "source_location": "L205"}, {"caller_nid": "runner_workerpool_stop", "callee": "values", "source_file": "backend/02_features/05_monitoring/workers/runner.py", "source_location": "L211"}, {"caller_nid": "runner_workerpool_stop", "callee": "getattr", "source_file": "backend/02_features/05_monitoring/workers/runner.py", "source_location": "L212"}, {"caller_nid": "runner_workerpool_stop", "callee": "stop_fn", "source_file": "backend/02_features/05_monitoring/workers/runner.py", "source_location": "L215"}, {"caller_nid": "runner_workerpool_stop", "callee": "cancel", "source_file": "backend/02_features/05_monitoring/workers/runner.py", "source_location": "L219"}, {"caller_nid": "runner_workerpool_stop", "callee": "wait", "source_file": "backend/02_features/05_monitoring/workers/runner.py", "source_location": "L221"}, {"caller_nid": "runner_workerpool_stop", "callee": "info", "source_file": "backend/02_features/05_monitoring/workers/runner.py", "source_location": "L222"}, {"caller_nid": "runner_workerpool_health", "callee": "replace", "source_file": "backend/02_features/05_monitoring/workers/runner.py", "source_location": "L227"}, {"caller_nid": "runner_workerpool_health", "callee": "now", "source_file": "backend/02_features/05_monitoring/workers/runner.py", "source_location": "L227"}, {"caller_nid": "runner_workerpool_health", "callee": "items", "source_file": "backend/02_features/05_monitoring/workers/runner.py", "source_location": "L228"}, {"caller_nid": "runner_workerpool_health", "callee": "get", "source_file": "backend/02_features/05_monitoring/workers/runner.py", "source_location": "L230"}, {"caller_nid": "runner_workerpool_health", "callee": "getattr", "source_file": "backend/02_features/05_monitoring/workers/runner.py", "source_location": "L231"}, {"caller_nid": "runner_workerpool_health", "callee": "total_seconds", "source_file": "backend/02_features/05_monitoring/workers/runner.py", "source_location": "L236"}]}